{
  "command_id": "53be8130",
  "executed_at": "2026-02-26T21:00:45.136857+00:00",
  "result": {
    "ok": true,
    "data": {
      "lines": [
        "2026-02-26 20:57:14,438 [WARNING] tradovate_api: Market data WebSocket closed: None None",
        "2026-02-26 20:57:14,438 [INFO] tradovate_api: Reconnecting in 4s (attempt 2/5)...",
        "2026-02-26 20:57:18,610 [INFO] websocket: Websocket connected",
        "2026-02-26 20:57:18,611 [INFO] tradovate_api: Market data WebSocket connected",
        "2026-02-26 20:57:18,726 [ERROR] tradovate_api: Market data WebSocket error: Connection to remote host was lost.",
        "2026-02-26 20:57:18,727 [ERROR] websocket: Connection to remote host was lost. - goodbye",
        "2026-02-26 20:57:18,727 [WARNING] tradovate_api: Market data WebSocket closed: None None",
        "2026-02-26 20:57:18,727 [INFO] tradovate_api: Reconnecting in 8s (attempt 3/5)...",
        "2026-02-26 20:57:26,898 [INFO] websocket: Websocket connected",
        "2026-02-26 20:57:26,898 [INFO] tradovate_api: Market data WebSocket connected",
        "2026-02-26 20:57:27,015 [ERROR] tradovate_api: Market data auth failed: {'s': 401, 'i': 1, 'd': '\"Expired Access Token\"'}",
        "2026-02-26 20:57:27,017 [ERROR] tradovate_api: Market data WebSocket error: Connection to remote host was lost.",
        "2026-02-26 20:57:27,018 [ERROR] websocket: Connection to remote host was lost. - goodbye",
        "2026-02-26 20:57:27,018 [WARNING] tradovate_api: Market data WebSocket closed: None None",
        "2026-02-26 20:57:27,018 [INFO] tradovate_api: Reconnecting in 16s (attempt 4/5)...",
        "2026-02-26 20:57:36,862 [WARNING] bot: WebSocket connection failed, falling back to REST polling",
        "2026-02-26 20:57:36,863 [INFO] tradovate_api: REST market data poller started (interval=5s)",
        "2026-02-26 20:57:36,863 [INFO] bot: Market data via REST polling (Yahoo Finance)",
        "2026-02-26 20:57:36,863 [INFO] tradovate_api: Subscribed to REST quotes: NQH6 -> NQ=F",
        "2026-02-26 20:57:36,863 [INFO] tradovate_api: Subscribed to REST quotes: ESH6 -> ES=F",
        "2026-02-26 20:57:36,863 [INFO] tradovate_api: Subscribed to REST quotes: GCH6 -> GC=F",
        "2026-02-26 20:57:36,863 [INFO] tradovate_api: Subscribed to REST quotes: CLJ6 -> CL=F",
        "2026-02-26 20:57:37,042 [WARNING] bot: Cash balance error: Account not found",
        "2026-02-26 20:57:37,043 [WARNING] bot: Account not found \u2014 forcing full re-authentication...",
        "2026-02-26 20:57:37,044 [INFO] tradovate_api: Loaded saved token, attempting renewal...",
        "2026-02-26 20:57:37,224 [INFO] tradovate_api: Token renewed. Expires: 2026-02-26 22:17:37.160000+00:00",
        "2026-02-26 20:57:37,226 [INFO] tradovate_api: Saved token renewed successfully",
        "2026-02-26 20:57:37,409 [INFO] bot: Re-auth OK: account=FNFTCHMOTITAPIRO67510 id=39996695",
        "2026-02-26 20:57:37,409 [INFO] bot: Initial balance: $50000.00 | drawdown_floor: $47500.00",
        "2026-02-26 20:57:37,409 [INFO] bot: Entering main loop...",
        "2026-02-26 20:57:37,585 [WARNING] bot: Cash balance error: Account not found",
        "2026-02-26 20:57:38,481 [INFO] bot: Status | balance=50000.00 | day_pnl=0.00 | to_floor=2500.00 | contracts=0/10 | trades=0/12 | locked=False",
        "2026-02-26 20:57:43,199 [INFO] websocket: Websocket connected",
        "2026-02-26 20:57:43,202 [INFO] tradovate_api: Market data WebSocket connected",
        "2026-02-26 20:57:43,321 [ERROR] tradovate_api: Market data auth failed: {'s': 401, 'i': 1, 'd': '\"Expired Access Token\"'}",
        "2026-02-26 20:57:43,322 [ERROR] tradovate_api: Market data WebSocket error: Connection to remote host was lost.",
        "2026-02-26 20:57:43,322 [ERROR] websocket: Connection to remote host was lost. - goodbye",
        "2026-02-26 20:57:43,323 [WARNING] tradovate_api: Market data WebSocket closed: None None",
        "2026-02-26 20:58:08,654 [WARNING] bot: Cash balance error: Account not found",
        "2026-02-26 20:58:08,835 [INFO] bot: Status | balance=50000.00 | day_pnl=0.00 | to_floor=2500.00 | contracts=0/10 | trades=0/12 | locked=False",
        "2026-02-26 20:58:39,077 [WARNING] bot: Cash balance error: Account not found",
        "2026-02-26 20:58:39,271 [INFO] bot: Status | balance=50000.00 | day_pnl=0.00 | to_floor=2500.00 | contracts=0/10 | trades=0/12 | locked=False",
        "2026-02-26 20:59:09,459 [WARNING] bot: Cash balance error: Account not found",
        "2026-02-26 20:59:09,643 [INFO] bot: Status | balance=50000.00 | day_pnl=0.00 | to_floor=2500.00 | contracts=0/10 | trades=0/12 | locked=False",
        "2026-02-26 20:59:39,811 [WARNING] bot: Cash balance error: Account not found",
        "2026-02-26 20:59:39,980 [INFO] bot: Status | balance=50000.00 | day_pnl=0.00 | to_floor=2500.00 | contracts=0/10 | trades=0/12 | locked=False",
        "2026-02-26 21:00:10,178 [WARNING] bot: Cash balance error: Account not found",
        "2026-02-26 21:00:10,423 [INFO] bot: Status | balance=50000.00 | day_pnl=0.00 | to_floor=2500.00 | contracts=0/10 | trades=0/12 | locked=False",
        "2026-02-26 21:00:40,626 [WARNING] bot: Cash balance error: Account not found",
        "2026-02-26 21:00:40,827 [INFO] bot: Status | balance=50000.00 | day_pnl=0.00 | to_floor=2500.00 | contracts=0/10 | trades=0/12 | locked=False"
      ],
      "count": 50
    }
  }
}