{
  "timestamp": "2026-03-05T15:48:30Z",
  "api_reachable": true,
  "authenticated": true,
  "auth_method": "server_token",
  "account": {
    "name": "FNFTCHMOTITAPIRO67510",
    "id": 39996695,
    "active": true
  },
  "balance": {
    "realizedPnl": null,
    "unrealizedPnl": null,
    "totalCashValue": 55408.24,
    "initialMargin": 0.0,
    "netLiq": 55408.24
  },
  "positions": [],
  "orders": [],
  "server": {
    "bot_dir": "/root/tradovate-bot",
    "bot_active": true,
    "bot_pid": "2277950",
    "uptime_since": "Thu 2026-03-05 14:35:30 UTC",
    "disk": "12%",
    "memory": "2355MB/7941MB (30%)",
    "hostname": "vmi3096165",
    "git_commit": "9da13e6 status: 2026-03-05 14:34 UTC | api=ok auth=None",
    "live_status": {
      "timestamp": "2026-03-05T15:48:24.161565+00:00",
      "timestamp_et": "2026-03-05T10:48:24.161590-05:00",
      "balance": 55408.24,
      "equity": 55408.24,
      "day_pnl": -1140.4000000000015,
      "peak_balance": 55408.24,
      "drawdown_floor": 52908.24,
      "distance_to_floor": 2500.0,
      "open_contracts": 0,
      "trades_today": 2,
      "locked": true,
      "lock_reason": "DAILY LOSS BRAKE: day P&L -1140.40 hit 60% of limit (-1000.00)",
      "environment": "demo",
      "dry_run": false,
      "active_symbols": [
        "NQ",
        "ES",
        "GC",
        "CL"
      ],
      "open_positions": {},
      "data_source": "rest_polling"
    },
    "journal_tail": "2026-03-05 15:38:33,384 [INFO] bot: Status | balance=55408.24 | day_pnl=-1140.40 | to_floor=2500.00 | contracts=0/10 | trades=2/16 | locked=True | data=REST\n2026-03-05 15:39:03,676 [INFO] bot: CashBalance: SOD=56548.64 totalPnL=-1140.40 => balance=55408.24 | realizedPnL=-1140.40 openPnL=0.00 netLiq=55408.24\n2026-03-05 15:39:03,888 [INFO] bot: Status | balance=55408.24 | day_pnl=-1140.40 | to_floor=2500.00 | contracts=0/10 | trades=2/16 | locked=True | data=REST\n2026-03-05 15:39:07,799 [INFO] tradovate_api: REST poller health: 1449 candles dispatched, 4 symbols tracked, 720 polls\n2026-03-05 15:39:39,079 [INFO] bot: CashBalance: SOD=56548.64 totalPnL=-1140.40 => balance=55408.24 | realizedPnL=-1140.40 openPnL=0.00 netLiq=55408.24\n2026-03-05 15:39:39,288 [INFO] bot: Status | balance=55408.24 | day_pnl=-1140.40 | to_floor=2500.00 | contracts=0/10 | trades=2/16 | locked=True | data=REST\n2026-03-05 15:40:09,542 [INFO] bot: CashBalance: SOD=56548.64 totalPnL=-1140.40 => balance=55408.24 | realizedPnL=-1140.40 openPnL=0.00 netLiq=55408.24\n2026-03-05 15:40:09,884 [INFO] bot: Status | balance=55408.24 | day_pnl=-1140.40 | to_floor=2500.00 | contracts=0/10 | trades=2/16 | locked=True | data=REST\n2026-03-05 15:40:10,310 [INFO] tradovate_api: REST poller health: 1474 candles dispatched, 4 symbols tracked, 732 polls\n2026-03-05 15:40:40,146 [INFO] bot: CashBalance: SOD=56548.64 totalPnL=-1140.40 => balance=55408.24 | realizedPnL=-1140.40 openPnL=0.00 netLiq=55408.24\n2026-03-05 15:40:40,411 [INFO] bot: Status | balance=55408.24 | day_pnl=-1140.40 | to_floor=2500.00 | contracts=0/10 | trades=2/16 | locked=True | data=REST\n2026-03-05 15:41:10,610 [INFO] bot: CashBalance: SOD=56548.64 totalPnL=-1140.40 => balance=55408.24 | realizedPnL=-1140.40 openPnL=0.00 netLiq=55408.24\n2026-03-05 15:41:10,813 [INFO] bot: Status | balance=55408.24 | day_pnl=-1140.40 | to_floor=2500.00 | contracts=0/10 | trades=2/16 | locked=True | data=REST\n2026-03-05 15:41:12,938 [INFO] tradovate_api: REST poller ",
    "bot_log_tail": "2026-03-05 15:44:44,165 [INFO] bot: Status | balance=55408.24 | day_pnl=-1140.40 | to_floor=2500.00 | contracts=0/10 | trades=2/16 | locked=True | data=REST\n2026-03-05 15:45:14,356 [INFO] bot: CashBalance: SOD=56548.64 totalPnL=-1140.40 => balance=55408.24 | realizedPnL=-1140.40 openPnL=0.00 netLiq=55408.24\n2026-03-05 15:45:14,601 [INFO] bot: Status | balance=55408.24 | day_pnl=-1140.40 | to_floor=2500.00 | contracts=0/10 | trades=2/16 | locked=True | data=REST\n2026-03-05 15:45:23,614 [INFO] tradovate_api: REST poller health: 1594 candles dispatched, 4 symbols tracked, 792 polls\n2026-03-05 15:45:44,604 [INFO] tradovate_api: Token expiring in 587s. Renewing...\n2026-03-05 15:45:44,787 [INFO] tradovate_api: Token renewed via demo.tradovateapi.com. Expires: 2026-03-05 17:05:44.726000+00:00\n2026-03-05 15:45:44,990 [INFO] bot: CashBalance: SOD=56548.64 totalPnL=-1140.40 => balance=55408.24 | realizedPnL=-1140.40 openPnL=0.00 netLiq=55408.24\n2026-03-05 15:45:45,696 [INFO] bot: Status | balance=55408.24 | day_pnl=-1140.40 | to_floor=2500.00 | contracts=0/10 | trades=2/16 | locked=True | data=REST\n2026-03-05 15:46:15,899 [INFO] bot: CashBalance: SOD=56548.64 totalPnL=-1140.40 => balance=55408.24 | realizedPnL=-1140.40 openPnL=0.00 netLiq=55408.24\n2026-03-05 15:46:16,101 [INFO] bot: Status | balance=55408.24 | day_pnl=-1140.40 | to_floor=2500.00 | contracts=0/10 | trades=2/16 | locked=True | data=REST\n2026-03-05 15:46:26,432 [INFO] tradovate_api: REST poller health: 1619 candles dispatched, 4 symbols tracked, 804 polls\n2026-03-05 15:46:46,710 [INFO] bot: CashBalance: SOD=56548.64 totalPnL=-1140.40 => balance=55408.24 | realizedPnL=-1140.40 openPnL=0.00 netLiq=55408.24\n2026-03-05 15:46:46,958 [INFO] bot: Status | balance=55408.24 | day_pnl=-1140.40 | to_floor=2500.00 | contracts=0/10 | trades=2/16 | locked=True | data=REST\n2026-03-05 15:47:17,363 [INFO] bot: CashBalance: SOD=56548.64 totalPnL=-1140.40 => balance=55408.24 | realizedPnL=-1140.40 openPnL=0.00 netLiq=55408.24\n2026",
    "cron_log_tail": "  Errors (1h): 0 | Warnings: 0\n  Signals today: 0\n\n[5/5] Live Status & System\n  live_status.json: exists (age: 20s)\n  Balance: $55408.24\n  Day P&L: $-1140.4000000000015\n  Trades today: 2\n  Locked: True\n  Active symbols: ['NQ', 'ES', 'GC', 'CL']\n  Disk: 12% | Memory: 29.9%\n\n============================================================\n  VERDICT: HEALTHY\n  Bot: ALIVE | Token: OK | Balance: OK | Log: FRESH\n============================================================\n\nReport: /root/tradovate-bot/connection_status.json\n[Thu Mar  5 15:45:05 UTC 2026] Status: bot_active=true, pid=2277950\n[Thu Mar  5 15:45:05 UTC 2026] No GH_PAT set \u2014 status written locally only."
  },
  "trading_activity": {
    "live_status": {
      "timestamp": "2026-03-05T15:48:24.161565+00:00",
      "timestamp_et": "2026-03-05T10:48:24.161590-05:00",
      "balance": 55408.24,
      "equity": 55408.24,
      "day_pnl": -1140.4000000000015,
      "peak_balance": 55408.24,
      "drawdown_floor": 52908.24,
      "distance_to_floor": 2500.0,
      "open_contracts": 0,
      "trades_today": 2,
      "locked": true,
      "lock_reason": "DAILY LOSS BRAKE: day P&L -1140.40 hit 60% of limit (-1000.00)",
      "environment": "demo",
      "dry_run": false,
      "active_symbols": [
        "NQ",
        "ES",
        "GC",
        "CL"
      ],
      "open_positions": {},
      "data_source": "rest_polling"
    },
    "token_status": "valid",
    "token_expiry": "2026-03-05T17:05:44.726000+00:00",
    "recent_signals": [],
    "recent_trades": [],
    "bot_log_tail": [
      "2026-03-05 15:42:42,350 [INFO] bot: Status | balance=55408.24 | day_pnl=-1140.40 | to_floor=2500.00 | contracts=0/10 | trades=2/16 | locked=True | data=REST",
      "2026-03-05 15:43:12,536 [INFO] bot: CashBalance: SOD=56548.64 totalPnL=-1140.40 => balance=55408.24 | realizedPnL=-1140.40 openPnL=0.00 netLiq=55408.24",
      "2026-03-05 15:43:12,725 [INFO] bot: Status | balance=55408.24 | day_pnl=-1140.40 | to_floor=2500.00 | contracts=0/10 | trades=2/16 | locked=True | data=REST",
      "2026-03-05 15:43:18,309 [INFO] tradovate_api: REST poller health: 1547 candles dispatched, 4 symbols tracked, 768 polls",
      "2026-03-05 15:43:42,919 [INFO] bot: CashBalance: SOD=56548.64 totalPnL=-1140.40 => balance=55408.24 | realizedPnL=-1140.40 openPnL=0.00 netLiq=55408.24",
      "2026-03-05 15:43:43,136 [INFO] bot: Status | balance=55408.24 | day_pnl=-1140.40 | to_floor=2500.00 | contracts=0/10 | trades=2/16 | locked=True | data=REST",
      "2026-03-05 15:44:13,338 [INFO] bot: CashBalance: SOD=56548.64 totalPnL=-1140.40 => balance=55408.24 | realizedPnL=-1140.40 openPnL=0.00 netLiq=55408.24",
      "2026-03-05 15:44:13,659 [INFO] bot: Status | balance=55408.24 | day_pnl=-1140.40 | to_floor=2500.00 | contracts=0/10 | trades=2/16 | locked=True | data=REST",
      "2026-03-05 15:44:20,897 [INFO] tradovate_api: REST poller health: 1571 candles dispatched, 4 symbols tracked, 780 polls",
      "2026-03-05 15:44:43,949 [INFO] bot: CashBalance: SOD=56548.64 totalPnL=-1140.40 => balance=55408.24 | realizedPnL=-1140.40 openPnL=0.00 netLiq=55408.24",
      "2026-03-05 15:44:44,165 [INFO] bot: Status | balance=55408.24 | day_pnl=-1140.40 | to_floor=2500.00 | contracts=0/10 | trades=2/16 | locked=True | data=REST",
      "2026-03-05 15:45:14,356 [INFO] bot: CashBalance: SOD=56548.64 totalPnL=-1140.40 => balance=55408.24 | realizedPnL=-1140.40 openPnL=0.00 netLiq=55408.24",
      "2026-03-05 15:45:14,601 [INFO] bot: Status | balance=55408.24 | day_pnl=-1140.40 | to_floor=2500.00 | contracts=0/10 | trades=2/16 | locked=True | data=REST",
      "2026-03-05 15:45:23,614 [INFO] tradovate_api: REST poller health: 1594 candles dispatched, 4 symbols tracked, 792 polls",
      "2026-03-05 15:45:44,604 [INFO] tradovate_api: Token expiring in 587s. Renewing...",
      "2026-03-05 15:45:44,787 [INFO] tradovate_api: Token renewed via demo.tradovateapi.com. Expires: 2026-03-05 17:05:44.726000+00:00",
      "2026-03-05 15:45:44,990 [INFO] bot: CashBalance: SOD=56548.64 totalPnL=-1140.40 => balance=55408.24 | realizedPnL=-1140.40 openPnL=0.00 netLiq=55408.24",
      "2026-03-05 15:45:45,696 [INFO] bot: Status | balance=55408.24 | day_pnl=-1140.40 | to_floor=2500.00 | contracts=0/10 | trades=2/16 | locked=True | data=REST",
      "2026-03-05 15:46:15,899 [INFO] bot: CashBalance: SOD=56548.64 totalPnL=-1140.40 => balance=55408.24 | realizedPnL=-1140.40 openPnL=0.00 netLiq=55408.24",
      "2026-03-05 15:46:16,101 [INFO] bot: Status | balance=55408.24 | day_pnl=-1140.40 | to_floor=2500.00 | contracts=0/10 | trades=2/16 | locked=True | data=REST",
      "2026-03-05 15:46:26,432 [INFO] tradovate_api: REST poller health: 1619 candles dispatched, 4 symbols tracked, 804 polls",
      "2026-03-05 15:46:46,710 [INFO] bot: CashBalance: SOD=56548.64 totalPnL=-1140.40 => balance=55408.24 | realizedPnL=-1140.40 openPnL=0.00 netLiq=55408.24",
      "2026-03-05 15:46:46,958 [INFO] bot: Status | balance=55408.24 | day_pnl=-1140.40 | to_floor=2500.00 | contracts=0/10 | trades=2/16 | locked=True | data=REST",
      "2026-03-05 15:47:17,363 [INFO] bot: CashBalance: SOD=56548.64 totalPnL=-1140.40 => balance=55408.24 | realizedPnL=-1140.40 openPnL=0.00 netLiq=55408.24",
      "2026-03-05 15:47:22,649 [INFO] bot: Status | balance=55408.24 | day_pnl=-1140.40 | to_floor=2500.00 | contracts=0/10 | trades=2/16 | locked=True | data=REST",
      "2026-03-05 15:47:29,288 [INFO] tradovate_api: REST poller health: 1644 candles dispatched, 4 symbols tracked, 816 polls",
      "2026-03-05 15:47:53,281 [INFO] bot: CashBalance: SOD=56548.64 totalPnL=-1140.40 => balance=55408.24 | realizedPnL=-1140.40 openPnL=0.00 netLiq=55408.24",
      "2026-03-05 15:47:53,617 [INFO] bot: Status | balance=55408.24 | day_pnl=-1140.40 | to_floor=2500.00 | contracts=0/10 | trades=2/16 | locked=True | data=REST",
      "2026-03-05 15:48:23,963 [INFO] bot: CashBalance: SOD=56548.64 totalPnL=-1140.40 => balance=55408.24 | realizedPnL=-1140.40 openPnL=0.00 netLiq=55408.24",
      "2026-03-05 15:48:24,160 [INFO] bot: Status | balance=55408.24 | day_pnl=-1140.40 | to_floor=2500.00 | contracts=0/10 | trades=2/16 | locked=True | data=REST"
    ],
    "journal_summary": {
      "total_trades": 0,
      "wins": 0,
      "losses": 0,
      "win_rate": 0,
      "total_pnl": 0
    },
    "trading_active": true,
    "websocket_connected": false,
    "errors_in_log": []
  },
  "errors": [],
  "debug": {
    "ssh_available": "true",
    "ssh_ok": "true",
    "ssh_output_len": 11941,
    "has_server_host": "true",
    "has_ssh_key": "true",
    "has_username": true,
    "username_len": 16,
    "has_password": true,
    "password_len": 9,
    "has_access_token": false,
    "username_first3": "FNF"
  }
}