{
  "timestamp": "2026-03-11T14:37:56Z",
  "api_reachable": true,
  "authenticated": true,
  "auth_method": "server_token",
  "account": {
    "name": "FNFTCHMOTITAPIRO67510",
    "id": 39996695,
    "active": true
  },
  "balance": {
    "realizedPnl": null,
    "unrealizedPnl": null,
    "totalCashValue": 59609.94,
    "initialMargin": 0.0,
    "netLiq": 59609.94
  },
  "positions": [],
  "orders": [],
  "server": {
    "bot_dir": "/root/tradovate-bot",
    "bot_active": true,
    "bot_pid": "93282",
    "uptime_since": "Wed 2026-03-11 11:55:23 UTC",
    "disk": "17%",
    "memory": "2713MB/7941MB (34%)",
    "hostname": "vmi3096165",
    "git_commit": "d031535 status: 2026-03-11 11:53 UTC | api=ok auth=server_token bot=running trading=active",
    "live_status": {
      "timestamp": "2026-03-11T14:37:37.366947+00:00",
      "timestamp_et": "2026-03-11T10:37:37.366973-04:00",
      "balance": 59609.94,
      "equity": 59609.94,
      "day_pnl": -1058.199999999997,
      "peak_balance": 59609.94,
      "drawdown_floor": 57109.94,
      "distance_to_floor": 2500.0,
      "open_contracts": 0,
      "trades_today": 0,
      "locked": true,
      "lock_reason": "DAILY LOSS BRAKE: day P&L -1058.20 hit 60% of limit (-1000.00)",
      "environment": "demo",
      "dry_run": false,
      "active_symbols": [
        "NQ",
        "ES",
        "GC",
        "CL"
      ]
    },
    "journal_tail": "2026-03-11 14:20:45,149 [INFO] bot: Status | balance=59609.94 | day_pnl=-1058.20 | to_floor=2500.00 | contracts=0/10 | trades=0/16 | locked=True\n2026-03-11 14:20:47,444 [INFO] tradovate_api: REST poller health: 3440 candles dispatched, 4 symbols tracked, 1632 polls\n2026-03-11 14:21:18,729 [INFO] bot: Status | balance=59609.94 | day_pnl=-1058.20 | to_floor=2500.00 | contracts=0/10 | trades=0/16 | locked=True\n2026-03-11 14:21:49,431 [INFO] bot: Status | balance=59609.94 | day_pnl=-1058.20 | to_floor=2500.00 | contracts=0/10 | trades=0/16 | locked=True\n2026-03-11 14:21:50,893 [INFO] tradovate_api: REST poller health: 3464 candles dispatched, 4 symbols tracked, 1644 polls\n2026-03-11 14:22:20,206 [INFO] bot: Status | balance=59609.94 | day_pnl=-1058.20 | to_floor=2500.00 | contracts=0/10 | trades=0/16 | locked=True\n2026-03-11 14:22:50,789 [INFO] bot: Status | balance=59609.94 | day_pnl=-1058.20 | to_floor=2500.00 | contracts=0/10 | trades=0/16 | locked=True\n2026-03-11 14:22:54,409 [INFO] tradovate_api: REST poller health: 3489 candles dispatched, 4 symbols tracked, 1656 polls\n2026-03-11 14:23:21,532 [INFO] bot: Status | balance=59609.94 | day_pnl=-1058.20 | to_floor=2500.00 | contracts=0/10 | trades=0/16 | locked=True\n2026-03-11 14:23:56,966 [INFO] bot: Status | balance=59609.94 | day_pnl=-1058.20 | to_floor=2500.00 | contracts=0/10 | trades=0/16 | locked=True\n2026-03-11 14:23:58,645 [INFO] tradovate_api: REST poller health: 3514 candles dispatched, 4 symbols tracked, 1668 polls\n2026-03-11 14:24:27,391 [INFO] bot: Status | balance=59609.94 | day_pnl=-1058.20 | to_floor=2500.00 | contracts=0/10 | trades=0/16 | locked=True\n2026-03-11 14:24:58,033 [INFO] bot: Status | balance=59609.94 | day_pnl=-1058.20 | to_floor=2500.00 | contracts=0/10 | trades=0/16 | locked=True\n2026-03-11 14:25:02,035 [INFO] tradovate_api: REST poller health: 3539 candles dispatched, 4 symbols tracked, 1680 polls\n2026-03-11 14:25:29,025 [INFO] bot: Status | balance=59609.94 | day_pnl=-1058.20 | to_floo",
    "bot_log_tail": "2026-03-11 14:31:16,591 [INFO] bot: Status | balance=59609.94 | day_pnl=-1058.20 | to_floor=2500.00 | contracts=0/10 | trades=0/16 | locked=True\n2026-03-11 14:31:23,543 [INFO] tradovate_api: REST poller health: 3693 candles dispatched, 4 symbols tracked, 1752 polls\n2026-03-11 14:31:49,594 [INFO] bot: Status | balance=59609.94 | day_pnl=-1058.20 | to_floor=2500.00 | contracts=0/10 | trades=0/16 | locked=True\n2026-03-11 14:32:20,103 [INFO] bot: Status | balance=59609.94 | day_pnl=-1058.20 | to_floor=2500.00 | contracts=0/10 | trades=0/16 | locked=True\n2026-03-11 14:32:27,756 [INFO] tradovate_api: REST poller health: 3718 candles dispatched, 4 symbols tracked, 1764 polls\n2026-03-11 14:32:50,747 [INFO] bot: Status | balance=59609.94 | day_pnl=-1058.20 | to_floor=2500.00 | contracts=0/10 | trades=0/16 | locked=True\n2026-03-11 14:33:21,573 [INFO] bot: Status | balance=59609.94 | day_pnl=-1058.20 | to_floor=2500.00 | contracts=0/10 | trades=0/16 | locked=True\n2026-03-11 14:33:32,729 [INFO] tradovate_api: REST poller health: 3745 candles dispatched, 4 symbols tracked, 1776 polls\n2026-03-11 14:33:53,511 [INFO] bot: Status | balance=59609.94 | day_pnl=-1058.20 | to_floor=2500.00 | contracts=0/10 | trades=0/16 | locked=True\n2026-03-11 14:34:24,335 [INFO] bot: Status | balance=59609.94 | day_pnl=-1058.20 | to_floor=2500.00 | contracts=0/10 | trades=0/16 | locked=True\n2026-03-11 14:34:36,130 [INFO] tradovate_api: REST poller health: 3770 candles dispatched, 4 symbols tracked, 1788 polls\n2026-03-11 14:34:55,228 [INFO] bot: Status | balance=59609.94 | day_pnl=-1058.20 | to_floor=2500.00 | contracts=0/10 | trades=0/16 | locked=True\n2026-03-11 14:35:31,265 [INFO] bot: Status | balance=59609.94 | day_pnl=-1058.20 | to_floor=2500.00 | contracts=0/10 | trades=0/16 | locked=True\n2026-03-11 14:35:39,769 [INFO] tradovate_api: REST poller health: 3797 candles dispatched, 4 symbols tracked, 1800 polls\n2026-03-11 14:36:02,372 [INFO] bot: Status | balance=59609.94 | day_pnl=-1058.20 | to_floo",
    "cron_log_tail": "  Errors (1h): 0 | Warnings: 0\n  Signals today: 0\n\n[5/5] Live Status & System\n  live_status.json: exists (age: 9s)\n  Balance: $59609.94\n  Day P&L: $-1058.199999999997\n  Trades today: 0\n  Locked: True\n  Active symbols: ['NQ', 'ES', 'GC', 'CL']\n  Disk: 17% | Memory: 34.3%\n\n============================================================\n  VERDICT: HEALTHY\n  Bot: ALIVE | Token: OK | Balance: OK | Log: FRESH\n============================================================\n\nReport: /root/tradovate-bot/connection_status.json\n[Wed Mar 11 14:35:05 UTC 2026] Status: bot_active=true, pid=93282\n[Wed Mar 11 14:35:05 UTC 2026] No GH_PAT set \u2014 status written locally only."
  },
  "trading_activity": {
    "live_status": {
      "timestamp": "2026-03-11T14:37:37.366947+00:00",
      "timestamp_et": "2026-03-11T10:37:37.366973-04:00",
      "balance": 59609.94,
      "equity": 59609.94,
      "day_pnl": -1058.199999999997,
      "peak_balance": 59609.94,
      "drawdown_floor": 57109.94,
      "distance_to_floor": 2500.0,
      "open_contracts": 0,
      "trades_today": 0,
      "locked": true,
      "lock_reason": "DAILY LOSS BRAKE: day P&L -1058.20 hit 60% of limit (-1000.00)",
      "environment": "demo",
      "dry_run": false,
      "active_symbols": [
        "NQ",
        "ES",
        "GC",
        "CL"
      ]
    },
    "token_status": "valid",
    "token_expiry": "2026-03-11T15:36:06.292000+00:00",
    "recent_signals": [],
    "recent_trades": [],
    "bot_log_tail": [
      "2026-03-11 14:27:32,047 [INFO] bot: Status | balance=59609.94 | day_pnl=-1058.20 | to_floor=2500.00 | contracts=0/10 | trades=0/16 | locked=True",
      "2026-03-11 14:28:03,219 [INFO] bot: Status | balance=59609.94 | day_pnl=-1058.20 | to_floor=2500.00 | contracts=0/10 | trades=0/16 | locked=True",
      "2026-03-11 14:28:13,705 [INFO] tradovate_api: REST poller health: 3619 candles dispatched, 4 symbols tracked, 1716 polls",
      "2026-03-11 14:28:33,724 [INFO] bot: Status | balance=59609.94 | day_pnl=-1058.20 | to_floor=2500.00 | contracts=0/10 | trades=0/16 | locked=True",
      "2026-03-11 14:29:04,276 [INFO] bot: Status | balance=59609.94 | day_pnl=-1058.20 | to_floor=2500.00 | contracts=0/10 | trades=0/16 | locked=True",
      "2026-03-11 14:29:16,798 [INFO] tradovate_api: REST poller health: 3643 candles dispatched, 4 symbols tracked, 1728 polls",
      "2026-03-11 14:29:35,037 [INFO] bot: Status | balance=59609.94 | day_pnl=-1058.20 | to_floor=2500.00 | contracts=0/10 | trades=0/16 | locked=True",
      "2026-03-11 14:30:05,665 [INFO] bot: Status | balance=59609.94 | day_pnl=-1058.20 | to_floor=2500.00 | contracts=0/10 | trades=0/16 | locked=True",
      "2026-03-11 14:30:20,357 [INFO] tradovate_api: REST poller health: 3666 candles dispatched, 4 symbols tracked, 1740 polls",
      "2026-03-11 14:30:41,150 [INFO] bot: Status | balance=59609.94 | day_pnl=-1058.20 | to_floor=2500.00 | contracts=0/10 | trades=0/16 | locked=True",
      "2026-03-11 14:31:16,591 [INFO] bot: Status | balance=59609.94 | day_pnl=-1058.20 | to_floor=2500.00 | contracts=0/10 | trades=0/16 | locked=True",
      "2026-03-11 14:31:23,543 [INFO] tradovate_api: REST poller health: 3693 candles dispatched, 4 symbols tracked, 1752 polls",
      "2026-03-11 14:31:49,594 [INFO] bot: Status | balance=59609.94 | day_pnl=-1058.20 | to_floor=2500.00 | contracts=0/10 | trades=0/16 | locked=True",
      "2026-03-11 14:32:20,103 [INFO] bot: Status | balance=59609.94 | day_pnl=-1058.20 | to_floor=2500.00 | contracts=0/10 | trades=0/16 | locked=True",
      "2026-03-11 14:32:27,756 [INFO] tradovate_api: REST poller health: 3718 candles dispatched, 4 symbols tracked, 1764 polls",
      "2026-03-11 14:32:50,747 [INFO] bot: Status | balance=59609.94 | day_pnl=-1058.20 | to_floor=2500.00 | contracts=0/10 | trades=0/16 | locked=True",
      "2026-03-11 14:33:21,573 [INFO] bot: Status | balance=59609.94 | day_pnl=-1058.20 | to_floor=2500.00 | contracts=0/10 | trades=0/16 | locked=True",
      "2026-03-11 14:33:32,729 [INFO] tradovate_api: REST poller health: 3745 candles dispatched, 4 symbols tracked, 1776 polls",
      "2026-03-11 14:33:53,511 [INFO] bot: Status | balance=59609.94 | day_pnl=-1058.20 | to_floor=2500.00 | contracts=0/10 | trades=0/16 | locked=True",
      "2026-03-11 14:34:24,335 [INFO] bot: Status | balance=59609.94 | day_pnl=-1058.20 | to_floor=2500.00 | contracts=0/10 | trades=0/16 | locked=True",
      "2026-03-11 14:34:36,130 [INFO] tradovate_api: REST poller health: 3770 candles dispatched, 4 symbols tracked, 1788 polls",
      "2026-03-11 14:34:55,228 [INFO] bot: Status | balance=59609.94 | day_pnl=-1058.20 | to_floor=2500.00 | contracts=0/10 | trades=0/16 | locked=True",
      "2026-03-11 14:35:31,265 [INFO] bot: Status | balance=59609.94 | day_pnl=-1058.20 | to_floor=2500.00 | contracts=0/10 | trades=0/16 | locked=True",
      "2026-03-11 14:35:39,769 [INFO] tradovate_api: REST poller health: 3797 candles dispatched, 4 symbols tracked, 1800 polls",
      "2026-03-11 14:36:02,372 [INFO] bot: Status | balance=59609.94 | day_pnl=-1058.20 | to_floor=2500.00 | contracts=0/10 | trades=0/16 | locked=True",
      "2026-03-11 14:36:36,006 [INFO] bot: Status | balance=59609.94 | day_pnl=-1058.20 | to_floor=2500.00 | contracts=0/10 | trades=0/16 | locked=True",
      "2026-03-11 14:36:43,477 [INFO] tradovate_api: REST poller health: 3823 candles dispatched, 4 symbols tracked, 1812 polls",
      "2026-03-11 14:37:06,560 [INFO] bot: Status | balance=59609.94 | day_pnl=-1058.20 | to_floor=2500.00 | contracts=0/10 | trades=0/16 | locked=True",
      "2026-03-11 14:37:37,347 [INFO] bot: Status | balance=59609.94 | day_pnl=-1058.20 | to_floor=2500.00 | contracts=0/10 | trades=0/16 | locked=True",
      "2026-03-11 14:37:46,785 [INFO] tradovate_api: REST poller health: 3848 candles dispatched, 4 symbols tracked, 1824 polls"
    ],
    "journal_summary": {
      "total_trades": 0,
      "wins": 0,
      "losses": 0,
      "win_rate": 0,
      "total_pnl": 0,
      "trades_today": 0
    },
    "trading_active": true,
    "websocket_connected": false,
    "errors_in_log": [],
    "today_trades": [],
    "today_fills": [
      {
        "id": 409583842201,
        "action": "Sell",
        "contractId": 3273620,
        "qty": 2,
        "price": 83.87,
        "timestamp": "2026-03-11T07:10:04.847Z"
      },
      {
        "id": 409583842241,
        "action": "Buy",
        "contractId": 3273620,
        "qty": 2,
        "price": 84.41,
        "timestamp": "2026-03-11T07:25:28.805Z"
      },
      {
        "id": 409583842216,
        "action": "Buy",
        "contractId": 4291092,
        "qty": 1,
        "price": 5192.7,
        "timestamp": "2026-03-11T07:17:39.031Z"
      },
      {
        "id": 409583842250,
        "action": "Sell",
        "contractId": 4291092,
        "qty": 1,
        "price": 5193.1,
        "timestamp": "2026-03-11T07:25:28.807Z"
      }
    ]
  },
  "errors": [],
  "debug": {
    "ssh_available": "true",
    "ssh_ok": "true",
    "ssh_output_len": 12180,
    "has_server_host": "true",
    "has_ssh_key": "true",
    "has_username": true,
    "username_len": 16,
    "has_password": true,
    "password_len": 9,
    "has_access_token": false,
    "username_first3": "FNF"
  }
}